mmpp/__init__.py
mmpp/batch_operations.py
mmpp/cli.py
mmpp/core.py
mmpp/logging_config.py
mmpp/paper.mplstyle
mmpp/plotting.py
mmpp/simulation.py
mmpp/fft/__init__.py
mmpp/fft/compute_fft.py
mmpp/fft/core.py
mmpp/fft/electromagnetic_analysis.py
mmpp/fft/main.py
mmpp/fft/modes.py
mmpp/fft/plot.py
mmpp/fonts/Arial/ARIALN.TTF
mmpp/fonts/Arial/ARIALNB.TTF
mmpp/fonts/Arial/ARIALNBI.TTF
mmpp/fonts/Arial/ARIALNI.TTF
mmpp/fonts/Arial/ARLRDBD.TTF
mmpp/fonts/Arial/Arimo Bold Italic for Powerline.ttf
mmpp/fonts/Arial/Arimo Bold for Powerline.ttf
mmpp/fonts/Arial/Arimo Italic for Powerline.ttf
mmpp/fonts/Arial/Arimo for Powerline.ttf
mmpp/fonts/Arial/arial.ttf
mmpp/fonts/Arial/arialbd.ttf
mmpp/fonts/Arial/arialbi.ttf
mmpp/fonts/Arial/ariali.ttf
mmpp/fonts/Arial/ariblk.ttf
mmpp-0.5.3.dist-info/METADATA
mmpp-0.5.3.dist-info/WHEEL
mmpp-0.5.3.dist-info/entry_points.txt
mmpp-0.5.3.dist-info/top_level.txt
mmpp-0.5.3.dist-info/RECORD
