Metadata-Version: 2.4
Name: mmpp
Version: 0.5.3
Summary: A library for MMPP (Micro Magnetic Post Processing) simulation and analysis
Home-page: https://github.com/mateuszzelent/mmpp
Author: Mateusz Zelent
Author-email: Mateusz Zelent <mateusz.zelent@amu.edu.pl>
License: MIT
Project-URL: Homepage, https://github.com/mateuszzelent/mmpp
Project-URL: Repository, https://github.com/mateuszzelent/mmpp
Project-URL: Issues, https://github.com/mateuszzelent/mmpp/issues
Classifier: Development Status :: 3 - Alpha
Classifier: Intended Audience :: Science/Research
Classifier: Operating System :: OS Independent
Classifier: Programming Language :: Python :: 3
Classifier: Programming Language :: Python :: 3.9
Classifier: Programming Language :: Python :: 3.10
Classifier: Programming Language :: Python :: 3.11
Classifier: Topic :: Scientific/Engineering
Classifier: Topic :: Scientific/Engineering :: Physics
Requires-Python: >=3.9
Requires-Dist: numpy>=1.20.0
Requires-Dist: pandas>=1.3.0
Requires-Dist: matplotlib>=3.5.0
Requires-Dist: pyzfn
Requires-Dist: zarr
Requires-Dist: rich
Requires-Dist: tqdm
Provides-Extra: dev
Requires-Dist: pytest>=6.0; extra == "dev"
Requires-Dist: pytest-cov; extra == "dev"
Requires-Dist: ruff; extra == "dev"
Requires-Dist: mypy; extra == "dev"
Requires-Dist: build; extra == "dev"
Requires-Dist: twine; extra == "dev"
Requires-Dist: sphinx>=4.0; extra == "dev"
Requires-Dist: sphinx-rtd-theme; extra == "dev"
Requires-Dist: sphinx-autodoc-typehints; extra == "dev"
Requires-Dist: myst-parser; extra == "dev"
Provides-Extra: interactive
Requires-Dist: itables; extra == "interactive"
Requires-Dist: IPython; extra == "interactive"
Requires-Dist: jupyter; extra == "interactive"
Provides-Extra: plotting
Requires-Dist: cmocean; extra == "plotting"
Dynamic: author
Dynamic: home-page
Dynamic: requires-python
